aio_redis_mq/__init__.py
aio_redis_mq/client.py
aio_redis_mq/consumer.py
aio_redis_mq/exceptions.py
aio_redis_mq/group.py
aio_redis_mq/group_consumer.py
aio_redis_mq/group_manger.py
aio_redis_mq/producer.py
aio_redis_mq/redispool.py
aio_redis_mq-2.0.0.dist-info/LICENSE
aio_redis_mq-2.0.0.dist-info/METADATA
aio_redis_mq-2.0.0.dist-info/WHEEL
aio_redis_mq-2.0.0.dist-info/top_level.txt
aio_redis_mq-2.0.0.dist-info/RECORD
