Metadata-Version: 2.1
Name: aio-redis-mq
Version: 2.0.0
Summary: Lightweight Message Queue & Broker base on async python redis streams
Home-page: http://github.com/kavinbj/aioRedisMQ
Author: kavinbj
Author-email: kwfelix@163.com
License: MIT
Keywords: asynchronous lightweight message queue system
Classifier: Development Status :: 5 - Production/Stable
Classifier: Framework :: AsyncIO
Classifier: License :: OSI Approved :: MIT License
Classifier: Programming Language :: Python :: 3
Classifier: Programming Language :: Python :: 3.7
Classifier: Programming Language :: Python :: 3.8
Classifier: Programming Language :: Python :: 3.9
Classifier: Topic :: Software Development
Classifier: Topic :: Software Development :: Libraries
Requires-Python: >=3.7
License-File: LICENSE
Requires-Dist: aioredis (>=2.0.0)
